pexpect_serialspawn/__init__.py
pexpect_serialspawn/serial_spawn.py
pexpect_serialspawn/stdin_helpers.py
pexpect_serialspawn-0.0.4.dist-info/METADATA
pexpect_serialspawn-0.0.4.dist-info/WHEEL
pexpect_serialspawn-0.0.4.dist-info/RECORD
