Metadata-Version: 2.4
Name: pexpect-serialspawn
Version: 0.0.4
Summary: Interact with serial devices using pexpect
Project-URL: Homepage, https://github.com/antoniovazquezblanco/pexpect-serialspawn
Project-URL: Bug Tracker, https://github.com/antoniovazquezblanco/pexpect-serialspawn/issues
Author-email: Antonio Vázquez Blanco <antoniovazquezblanco@gmail.com>
Classifier: License :: OSI Approved :: MIT License
Classifier: Operating System :: OS Independent
Classifier: Programming Language :: Python :: 3
Requires-Python: >=3.0
Requires-Dist: pexpect
Requires-Dist: pyserial
